{
  "México": [
    {
      "pais": "México",
      "estado": "Ciudad de México",
      "ciudad": "Ciudad de México",
      "direccion": "Paseo de la Reforma 305",
      "codigo_postal": "01000",
      "telefono": "+52 1 555-1234-5678"
    },
    {
      "pais": "México",
      "estado": "Jalisco",
      "ciudad": "Guadalajara",
      "direccion": "Av. Juárez 976",
      "codigo_postal": "44100",
      "telefono": "+52 1 333-5678-9101"
    },
    {
      "pais": "México",
      "estado": "Nuevo León",
      "ciudad": "Monterrey",
      "direccion": "Av. Constitución 1000",
      "codigo_postal": "64000",
      "telefono": "+52 1 818-3456-7890"
    }
  ],
  "Estados Unidos": [
    {
      "pais": "Estados Unidos",
      "estado": "Nueva York",
      "ciudad": "Nueva York",
      "direccion": "350 5th Ave",
      "codigo_postal": "10001",
      "telefono": "+1 (212) 123-4567"
    },
    {
      "pais": "Estados Unidos",
      "estado": "California",
      "ciudad": "Los Ángeles",
      "direccion": "1111 S Figueroa St",
      "codigo_postal": "90001",
      "telefono": "+1 (213) 234-5678"
    },
    {
      "pais": "Estados Unidos",
      "estado": "California",
      "ciudad": "San Francisco",
      "direccion": "151 3rd St",
      "codigo_postal": "94102",
      "telefono": "+1 (415) 345-6789"
    }
  ],
  "Brasil": [
    {
      "pais": "Brasil",
      "estado": "São Paulo",
      "ciudad": "São Paulo",
      "direccion": "Av. Paulista 1578",
      "codigo_postal": "01000-000",
      "telefono": "+55 11 912345678"
    },
    {
      "pais": "Brasil",
      "estado": "Río de Janeiro",
      "ciudad": "Río de Janeiro",
      "direccion": "Av. Atlântica 1702",
      "codigo_postal": "20000-000",
      "telefono": "+55 21 923456789"
    },
    {
      "pais": "Brasil",
      "estado": "Distrito Federal",
      "ciudad": "Brasilia",
      "direccion": "Esplanada dos Ministérios",
      "codigo_postal": "70000-000",
      "telefono": "+55 61 934567890"
    }
  ]
}
